{
  "generator-jhipster": {
    "applicationType": "microservice",
    "authenticationType": "jwt",
    "baseName": "testweb",
    "blueprints": [],
    "buildTool": "maven",
    "cacheProvider": "no",
    "clientFramework": "angularX",
    "clientPackageManager": "npm",
    "clientTheme": "none",
    "clientThemeVariant": "",
    "creationTimestamp": 1676635991702,
    "databaseType": "sql",
    "devDatabaseType": "h2Disk",
    "devServerPort": 4200,
    "dtoSuffix": "DTO",
    "enableGradleEnterprise": false,
    "enableHibernateCache": false,
    "enableSwaggerCodegen": false,
    "enableTranslation": true,
    "entitySuffix": "",
    "gitCompany": "",
    "jhiPrefix": "jhi",
    "jhipsterVersion": "7.9.3",
    "jwtSecretKey": "NzgxOGQyZjU3NTMyZmFhZTgzNjE3ZWNjNWFhM2UzODA4NDgzOGE5YmNhNTI3NzViNWIyYTBhNTA2MmQ2ZjFmNzVhYWQ3MWMwNTFmMjY3YTMwNzI4Nzg1NDlhMzI5YWRhZTdkOTc2M2QzOGY0ODYxZThmZDhjMjhiMDJmZWU1Mzc=",
    "languages": ["en"],
    "messageBroker": false,
    "microfrontend": false,
    "nativeLanguage": "en",
    "otherModules": [],
    "packageFolder": "com/mycompany/myapp",
    "packageName": "com.mycompany.myapp",
    "pages": [],
    "prodDatabaseType": "postgresql",
    "reactive": false,
    "searchEngine": false,
    "serverPort": 8081,
    "serviceDiscoveryType": "eureka",
    "skipCheckLengthOfIdentifier": false,
    "skipClient": false,
    "skipFakeData": false,
    "skipUserManagement": true,
    "testFrameworks": [],
    "useSass": true,
    "websocket": false,
    "withAdminUi": false
  },
  "git-provider": "GitHub",
  "git-company": "SaidJumayev19980828",
  "repository-name": "jhipster-sample-application1"
}
